temper_syntax/__init__.py
temper_syntax/__init__.py.map
temper_syntax/pygments.py
temper_syntax/pygments.py.map
temper_syntax/temper_pygments.py
temper_syntax/temper_pygments.py.map
temper_syntax/temper_syntax.py
temper_syntax/temper_syntax.py.map
temper_syntax-0.6.0.dist-info/METADATA
temper_syntax-0.6.0.dist-info/WHEEL
temper_syntax-0.6.0.dist-info/RECORD
