Metadata-Version: 2.4
Name: temper-syntax
Version: 0.6.0
License: LicenseRef-Proprietary
Requires-Python: >=3.11
Requires-Dist: temper-core==0.6.0
